fast_trans_obj/__init__.py
fast_trans_obj/tcp_client.py
fast_trans_obj-0.0.6.dist-info/LICENSE
fast_trans_obj-0.0.6.dist-info/METADATA
fast_trans_obj-0.0.6.dist-info/WHEEL
fast_trans_obj-0.0.6.dist-info/top_level.txt
fast_trans_obj-0.0.6.dist-info/RECORD
