Metadata-Version: 2.1
Name: fast-trans-obj
Version: 0.0.6
Summary: A simple tools to trans obj to rpc
Home-page: https://github.com/
Author: cg_now
Author-email: 1939296965@qq.com
License: UNKNOWN
Platform: UNKNOWN
Classifier: Programming Language :: Python :: 3
Classifier: License :: OSI Approved :: MIT License
Classifier: Operating System :: OS Independent
Requires-Python: >=3.1
License-File: LICENSE
Requires-Dist: asyncio
